{
    "profiles" : [
        {
            "favourite_profiles" : [
                "user_B"
            ],
            "firstname" : "jim",
            "address" : {
                "country" : "",
                "city" : "",
                "street" : "",
                "postcode" : "SA1456",
                "houseNo" : 1
            },
            "surname" : "something",
            "avatar" : "file:data/avatars/user_AAvatar.png",
            "mobileNo" : "123456789",
            "username" : "user_A"
        },
        {
            "favourite_profiles" : [],
            "firstname" : "bob",
            "address" : {
                "country" : "",
                "city" : "",
                "street" : "",
                "postcode" : "SA1321",
                "houseNo" : 1
            },
            "surname" : "person",
            "avatar" : "file:data/avatars/user_BAvatar.png",
            "mobileNo" : "123456789",
            "username" : "user_B"
        },
        {
            "favourite_profiles" : [],
            "firstname" : "jon",
            "address" : {
                "country" : "",
                "city" : "",
                "street" : "",
                "postcode" : "SA1351",
                "houseNo" : 1
            },
            "surname" : "snow",
            "avatar" : "file:data/avatars/img.png",
            "mobileNo" : "123456789",
            "username" : "user_C"
        },
        {
            "favourite_profiles" : [],
            "firstname" : "Aleksandr",
            "address" : {
                "country" : "",
                "city" : "",
                "street" : "",
                "postcode" : "",
                "houseNo" : 0
            },
            "surname" : "Slobodov",
            "avatar" : "file:data/avatars/default_avatars/img5.png",
            "mobileNo" : "89257382222",
            "username" : "hadalhw17"
        },
        {
            "favourite_profiles" : [
                "user_A",
                "user_B",
                "user_C",
                "hadalhw17"
            ],
            "firstname" : "Tom",
            "address" : {
                "country" : "",
                "city" : "",
                "street" : "",
                "postcode" : "",
                "houseNo" : 0
            },
            "surname" : "Street",
            "avatar" : "file:data/avatars/BrotherhoodOfHamAvatar.png",
            "mobileNo" : "123456678",
            "username" : "BrotherhoodOfHam"
        },
        {
            "favourite_profiles" : [],
            "firstname" : "asdasd",
            "address" : {
                "country" : "",
                "city" : "",
                "street" : "",
                "postcode" : "",
                "houseNo" : 0
            },
            "surname" : "asdasfaa",
            "avatar" : "file:data/avatars/img.png",
            "mobileNo" : "asdfasda",
            "username" : "asfasga"
        },
        {
            "favourite_profiles" : [],
            "firstname" : "",
            "address" : {
                "country" : "",
                "city" : "",
                "street" : "",
                "postcode" : "",
                "houseNo" : 0
            },
            "surname" : "",
            "avatar" : "file:data/avatars/img.png",
            "mobileNo" : "",
            "username" : ""
        },
        {
            "favourite_profiles" : [],
            "firstname" : "sdf",
            "address" : {
                "country" : "",
                "city" : "",
                "street" : "",
                "postcode" : "",
                "houseNo" : 0
            },
            "surname" : "sdf",
            "avatar" : "file:data/avatars/img.png",
            "mobileNo" : "112231",
            "username" : "sdf"
        }
    ],
    "auctions" : [
        {
            "seller" : "user_B",
            "comments" : [
                {
                    "profile" : "user_B",
                    "text" : "very unhelpful comment that serves no purpose at all."
                },
                {
                    "profile" : "hadalhw17",
                    "text" : "Fuck"
                },
                {
                    "profile" : "user_A",
                    "text" : "testing testing"
                }
            ],
            "bids" : [
                {
                    "date" : "Dec 10, 2017",
                    "amount" : 1000001,
                    "bidder" : "user_A"
                },
                {
                    "date" : "Dec 10, 2017",
                    "amount" : 1000002,
                    "bidder" : "user_B"
                },
                {
                    "date" : "Dec 10, 2017",
                    "amount" : 2000000,
                    "bidder" : "user_A"
                },
                {
                    "date" : "Dec 10, 2017",
                    "amount" : 2000001,
                    "bidder" : "user_B"
                }
            ],
            "max_bids" : 5,
            "artwork" : {
                "date" : "Dec 10, 2017",
                "year" : 1503,
                "name" : "Mona Lisa",
                "width" : 0.53,
                "photo" : "file:data/artworks/img2.png",
                "reserve_price" : 1000000,
                "type" : "PAINTING",
                "desc" : "Mona Lisa",
                "height" : 0.77
            }
        },
        {
            "seller" : "user_C",
            "comments" : [
                {
                    "profile" : "user_A",
                    "text" : "some comment about the auction"
                },
                {
                    "profile" : "user_C",
                    "text" : "some other comment about the auction"
                },
                {
                    "profile" : "user_A",
                    "text" : "12348923948 238947923 89 239"
                }
            ],
            "bids" : [],
            "max_bids" : 5,
            "artwork" : {
                "date" : "Dec 10, 2017",
                "year" : 1889,
                "name" : "The Starry Night",
                "width" : 0.92,
                "photo" : "file:data/artworks/img1.png",
                "reserve_price" : 123000,
                "type" : "PAINTING",
                "desc" : "The Starry Night",
                "height" : 0.74
            }
        },
        {
            "seller" : "hadalhw17",
            "comments" : [],
            "bids" : [],
            "max_bids" : 5,
            "artwork" : {
                "date" : "Dec 10, 2017",
                "year" : 123,
                "name" : "Mona",
                "width" : 2.0,
                "photo" : "file:data/avatars/hadalhw170Avatar.png",
                "reserve_price" : 123,
                "type" : "PAINTING",
                "desc" : "Mona",
                "height" : 2.0
            }
        },
        {
            "seller" : "hadalhw17",
            "comments" : [],
            "bids" : [],
            "max_bids" : 5,
            "artwork" : {
                "date" : "Dec 10, 2017",
                "year" : 123,
                "name" : "asd",
                "width" : 123.0,
                "photo" : "file:data/avatars/hadalhw171Avatar.png",
                "reserve_price" : 123,
                "type" : "PAINTING",
                "desc" : "asd",
                "height" : 123.0
            }
        },
        {
            "seller" : "user_C",
            "comments" : [],
            "bids" : [],
            "max_bids" : 5,
            "artwork" : {
                "date" : "Dec 10, 2017",
                "depth" : 20.0,
                "year" : 2017,
                "name" : "Gorilla Head",
                "width" : 20.0,
                "photo" : "file:data/avatars/user_C1Avatar.png",
                "reserve_price" : 100,
                "type" : "SCULPTURE",
                "desc" : "Gorilla Head",
                "height" : 20.0
            }
        },
        {
            "seller" : "hadalhw17",
            "comments" : [],
            "bids" : [],
            "max_bids" : 2,
            "artwork" : {
                "date" : "Jan 12, 1913",
                "depth" : 123.0,
                "year" : 12312,
                "name" : "Sculpture1",
                "width" : 123.0,
                "photo" : "file:data/artworks/hadalhw172Artwork.png",
                "reserve_price" : 2,
                "type" : "SCULPTURE",
                "desc" : "Sculpture1",
                "height" : 123.0
            }
        }
    ]
}
